Metadata-Version: 1.1
Name: django-singlelogin
Version: 0.0.3
Summary: A small example package
Home-page: https://github.com/pypa/sampleproject
Author: Example Author
Author-email: aakashjoshi448@gmail.com
License: UNKNOWN
Platform: UNKNOWN
Classifier: Programming Language :: Python :: 3
Classifier: License :: OSI Approved :: MIT License
Classifier: Operating System :: OS Independent
